{"VTuber":{"id":"28c152a7489b4402960bd4bd36b7229b","activity":"active","name":"貓又徒名","imgUrl":"https://yt3.ggpht.com/DVghzx4Z2lh749eEmKELw3_13N_MJtl3LM1ohVYP6hik1L3sG7UX_k_uzv4XY59ePre_TxJ2tw=s240-c-k-c0x00ffffff-no-rj","YouTube":{"subscriber":{"tag":"has","count":389},"id":"UCvZ8gkVjVDt0cjBSQVnoFwQ"},"Twitch":{"follower":{"tag":"has","count":94},"id":"koyokainekomata"},"popularVideo":{"type":"YouTube","id":"KJj2XgZLUHU"},"nationality":"TW","debutDate":"2024-01-17","livestreams":[{"title":"1月社畜總表~歡迎關注卯貓~點讚訂閱","videoUrl":"https://www.youtube.com/watch?v=iNmvKGReouo","thumbnailUrl":"https://i.ytimg.com/vi/iNmvKGReouo/mqdefault_live.jpg","startTime":"2026-10-31T15:45:00.0000000\u002B00:00"}]}}