{"VTuber":{"id":"342f808864164047acc8ddffe88c9618","activity":"active","name":"逆NeePlus","imgUrl":"https://static-cdn.jtvnw.net/jtv_user_pictures/70e1c334-b36b-4e16-b602-c91fa118b8bf-profile_image-300x300.png","YouTube":{"subscriber":{"tag":"has","count":173},"id":"UCK_IDjsBk5hEKaLHc6d2bkQ"},"Twitch":{"follower":{"tag":"has","count":1244},"id":"nee606"},"popularVideo":{"type":"Twitch","id":"2387873265"},"nationality":"TW","debutDate":"2024-07-12","livestreams":[{"title":"3/6 逆 -【早安雜談】沒出息沒關係 有氣息已經很棒了！ ｜3月訂閱獎勵DC領取｜訂閱獎勵活動到3/14｜!魔儲 !AHN !DC","videoUrl":"https://www.twitch.tv/nee606","thumbnailUrl":"https://static-cdn.jtvnw.net/previews-ttv/live_user_nee606-178x100.jpg","startTime":"2025-03-06T02:20:41.0000000\u002B00:00"}]}}