{"VTuber":{"id":"3a43445829024217b728d04d5398b61c","activity":"active","name":"悠妮涅可","imgUrl":"https://yt3.ggpht.com/aiTLHEOn160UlrrA3tOCAuulmlN52P8G6UTYJVZ30tEcEg6NKpQQsGjKGk08nAWpLdcLzfgQKA=s240-c-k-c0x00ffffff-no-rj","YouTube":{"subscriber":{"tag":"has","count":3480},"id":"UCxR4d1Wq7BRNtYIAmJsnBkA"},"popularVideo":{"type":"YouTube","id":"XcAxt1cFfjk"},"group":"終焉理想庭","nationality":"TW","debutDate":"2022-05-21","livestreams":[{"title":"【手作】初見大歡迎~一起來許願吧 ฅ•ω•ฅ #vtuber #雜談 #新年2025","videoUrl":"https://www.youtube.com/watch?v=-8OzAZo38aE","thumbnailUrl":"https://i.ytimg.com/vi/-8OzAZo38aE/mqdefault_live.jpg","startTime":"2025-01-19T07:47:24.0000000\u002B00:00"}]}}