{"VTuber":{"id":"4de233ea7dfc4a7da1738ab627babd48","activity":"active","name":"伊理","imgUrl":"https://yt3.ggpht.com/gp3xWzGxRFO9u_eZbDvJ9ktKm-OXTfcpHiwLagbUiWt0zr_wIIEFWe1M_-DILEGr31MkF2Fj=s240-c-k-c0x00ffffff-no-rj","YouTube":{"subscriber":{"tag":"has","count":461},"id":"UCcZMCKa_ulPYA72jTAc9V3Q"},"popularVideo":{"type":"YouTube","id":"YhFy-4Ohu1k"},"group":"地下軼樓","nationality":"TW","debutDate":"2022-07-07","livestreams":[{"title":"【PC魔物獵人世界-冰原】MHW ep.23 絢輝or聚魔，這是個艱難的問題 マムタロトか導きの地か、どっち！[日本語/EN\uD83D\uDC4C/初見歓迎] #モンハン #mhwib","videoUrl":"https://www.youtube.com/watch?v=7qbnsy3Fa-U","thumbnailUrl":"https://i.ytimg.com/vi/7qbnsy3Fa-U/mqdefault_live.jpg","startTime":"2025-02-06T12:30:00.0000000\u002B00:00"},{"title":"【PTCG LIVE】I標異軍突起\u0026口袋版卡片交換! Ⅰレギュの優勝デッキとポケポケの交換機能![日本語/EN⭕] #ptcgl #ポケカ #PTCG","videoUrl":"https://www.youtube.com/watch?v=N236Mrgl9KQ","thumbnailUrl":"https://i.ytimg.com/vi/N236Mrgl9KQ/mqdefault_live.jpg","startTime":"2025-02-07T13:00:00.0000000\u002B00:00"}]}}