{"VTuber":{"id":"4f5a88e0193a4c948f7e84c56303db82","activity":"preparing","name":"Yuki 白昭雪","imgUrl":"https://yt3.ggpht.com/E-tiSSy8-4BF44WyYg8Q1VLA6UTHh_t480MGd8YvJ9DgMHqD6mElg5s8VJ06gAOViTTe_wbHqw=s240-c-k-c0x00ffffff-no-rj","YouTube":{"subscriber":{"tag":"has","count":381},"id":"UC_dwiOGE_uWNYtbyFg1PNeg"},"popularVideo":{"type":"YouTube","id":"R8J7PfGBTPA"},"group":"恋Vaichu","nationality":"TW","debutDate":"2025-03-12","livestreams":[{"title":"【初配信】來跟昭雪一起玩吧！  #昭昭幕幕 #螢窗雪案","videoUrl":"https://www.youtube.com/watch?v=kkGPHQpmji8","thumbnailUrl":"https://i.ytimg.com/vi/kkGPHQpmji8/mqdefault_live.jpg","startTime":"2025-03-12T13:00:00.0000000\u002B00:00"}]}}