{"VTuber":{"id":"60ae2b3fd2254689bb65c216a0a09605","activity":"preparing","name":"耀 Akari","imgUrl":"https://yt3.ggpht.com/LeYMC7jRKQ70GWp_sCQf4G_lwY4qCTJV9BfiJBDPlxX2i3EoqFwoqW41fGuv8UJnhSqI9GUG6qc=s240-c-k-c0x00ffffff-no-rj","YouTube":{"subscriber":{"tag":"has","count":7610},"id":"UC1U_NwxubHPnWzV-LcvoBpg"},"Twitch":{"follower":{"tag":"has","count":131},"id":"ouqfxxk"},"popularVideo":{"type":"YouTube","id":"hwQPcCXusT8"},"nationality":"TW","livestreams":[{"title":"ʚ⊹耀廚房⊹ɞ  開開心心又甜蜜的水果三明治喜歡你","videoUrl":"https://www.youtube.com/watch?v=KZaXhce-ZTw","thumbnailUrl":"https://i.ytimg.com/vi/KZaXhce-ZTw/mqdefault_live.jpg","startTime":"2025-01-04T12:04:23.0000000\u002B00:00"}]}}