{"VTuber":{"id":"63f727e673b9460abd6f7079bcbb1865","activity":"active","name":"穎兒Yinger","imgUrl":"https://yt3.ggpht.com/TRJK393HmRoWGGo71VUND1OcPyQQJxiud8sBgh9XYXYzwEvlPKZXeRgHElheNNzxF4mu1TrbmQ=s240-c-k-c0x00ffffff-no-rj","YouTube":{"subscriber":{"tag":"has","count":1680},"id":"UCGjiIw0elNTMRJHSi223t3A"},"popularVideo":{"type":"YouTube","id":"DVPVhp59Ufg"},"nationality":"TW","debutDate":"2024-06-12","livestreams":[{"title":"《 第五人格 / Identity V 》01 / 16 - 廠長溯迴也太年輕了，先知的布料好像有點少 ~【穎兒Yinger】","videoUrl":"https://www.youtube.com/watch?v=Lmf8ATFQssY","thumbnailUrl":"https://i.ytimg.com/vi/Lmf8ATFQssY/mqdefault_live.jpg","startTime":"2025-01-16T10:58:06.0000000\u002B00:00"}]}}