{"VTuber":{"id":"76d68171666847cc913328359037139c","activity":"active","name":"優娜","imgUrl":"https://yt3.ggpht.com/LN6QU6KIp6DR15cXQDI7xRCLYZhl7lvbliRNYynWUM-GujJqspCcdMgXEERDndBSz-MCoyg5wc0=s240-c-k-c0x00ffffff-no-rj","YouTube":{"subscriber":{"tag":"has","count":7520},"id":"UC8oeG5FNGxf3GMcKTGzCxbw"},"Twitch":{"follower":{"tag":"has","count":766},"id":"lanauna_0404"},"popularVideo":{"type":"YouTube","id":"u0fiZBmwctI"},"nationality":"TW","debutDate":"2024-10-12","livestreams":[{"title":"ARAM觀眾場 不連贏兩把不下播! 參加請先加入DC | 菈娜優娜 Una #初見歡迎","videoUrl":"https://www.twitch.tv/lanauna_0404","thumbnailUrl":"https://static-cdn.jtvnw.net/previews-ttv/live_user_lanauna_0404-178x100.jpg","startTime":"2025-01-27T06:27:31.0000000\u002B00:00"},{"title":"【ARAM觀眾場】我就不信了 中止連敗！不連贏兩把不下播！ 參加方式看資訊欄 【菈娜優娜】","videoUrl":"https://www.youtube.com/watch?v=aFRjXU1cITk","thumbnailUrl":"https://i.ytimg.com/vi/aFRjXU1cITk/mqdefault_live.jpg","startTime":"2025-01-27T06:30:00.0000000\u002B00:00"},{"title":"【VLOG】老虎姬轉生成為喵女僕？！反正都是貓科動物~喵嗚~阿發發居然最後....？女僕裝未免也太緊了吧!  台北酒吧推薦！FT.阿發發、喵屋 Meow House   #18","videoUrl":"https://www.youtube.com/watch?v=Pc1tdION9eE","thumbnailUrl":"https://i.ytimg.com/vi/Pc1tdION9eE/mqdefault.jpg","startTime":"2025-01-29T10:00:00.0000000\u002B00:00"}]}}