{"VTuber":{"id":"7b58646f89cb4b7cbcdce819499c475f","activity":"active","name":"露諾莉雅•因卡倫","imgUrl":"https://yt3.ggpht.com/BoYGAsuQpksrfhwNFXemVM_gtnHIuEkFGUU75IejbuhdESoL_A2Zc_4TNUXG7FXSB3pO_RqD=s240-c-k-c0x00ffffff-no-rj","YouTube":{"subscriber":{"tag":"has","count":16200},"id":"UC4Rcu4Q_hbg4ZSvVyT2UXbg"},"popularVideo":{"type":"YouTube","id":"lFlXwVwKIV4"},"nationality":"TW","debutDate":"2022-10-15","livestreams":[{"title":"【姚淬華】大喜 【原創PV】","videoUrl":"https://www.youtube.com/watch?v=7VZ7EfmvkTk","thumbnailUrl":"https://i.ytimg.com/vi/7VZ7EfmvkTk/mqdefault.jpg","startTime":"2025-02-16T13:00:00.0000000\u002B00:00"},{"title":"【魔王診間】EP5\uD83D\uDE16牙齒敏感大哉問\uD83D\uDD0D️ Ft.  阿金@ajing2733 Roliand老練的大喇叭@roliand1014  【露諾莉雅•因卡倫】#魔王降臨","videoUrl":"https://www.youtube.com/watch?v=ad0siMka_Tg","thumbnailUrl":"https://i.ytimg.com/vi/ad0siMka_Tg/mqdefault_live.jpg","startTime":"2025-02-16T13:30:00.0000000\u002B00:00"}]}}