{"VTuber":{"id":"80b6efc8007f4f6d84ce2f93862ae319","activity":"active","name":"李亭襄","imgUrl":"https://yt3.ggpht.com/zDNhkNAbhaC4IL3hHi3mWiDBzygbiLPXUP6Twpf0K_ytRwkaFgM4gNBdB5XI3uypvSh9KSbW=s240-c-k-c0x00ffffff-no-rj","YouTube":{"subscriber":{"tag":"has","count":528},"id":"UCB0dbHnZ044lKq_4eGQDmZA"},"popularVideo":{"type":"YouTube","id":"wDWZB5I7lmw"},"nationality":"TW","livestreams":[{"title":"[Vtuber李亭襄] 紅燒天堂(x) 緋染天空 (Heaven Burns Red) #29 主線劇情第五章中篇Part2- 世界的終結與白色的咒語 Day10-","videoUrl":"https://www.youtube.com/watch?v=u_jsjvzgNss","thumbnailUrl":"https://i.ytimg.com/vi/u_jsjvzgNss/mqdefault_live.jpg","startTime":"2025-03-04T13:51:13.0000000\u002B00:00"}]}}