{"VTuber":{"id":"b9086ee5f7b54353a5ba85c973b2e2af","activity":"active","name":"狸屋ゼロ","imgUrl":"https://yt3.ggpht.com/XtldALc3sH-lHt8pl7Ph7mwKnzIDdgiXEloRwU6a4qsp2k7IrQXIsOMYCKYJ9axLuHc3csjdXA=s240-c-k-c0x00ffffff-no-rj","YouTube":{"subscriber":{"tag":"has","count":888},"id":"UCTWARDuptsuZaOGPMiZ-EaA"},"popularVideo":{"type":"YouTube","id":"UmZfMBlvyw8"},"nationality":"TW","debutDate":"2024-06-21","livestreams":[{"title":"\\ ⍥ / Valley Girl in TAIWAN 加州女孩開箱台灣小吃\uD83D\uDC41️\uD83D\uDC44\uD83D\uDC41️｡♡  \\ ⍥ /  #台灣vtuber #開箱 #吃播 #愛台灣","videoUrl":"https://www.youtube.com/watch?v=va3nzfOo1Qc","thumbnailUrl":"https://i.ytimg.com/vi/va3nzfOo1Qc/mqdefault_live.jpg","startTime":"2025-02-15T05:30:00.0000000\u002B00:00"}]}}