{"VTuber":{"id":"dbe3f9880dec4a03bcc1943343455a6c","activity":"active","name":"天犂謬那","imgUrl":"https://yt3.ggpht.com/P04CP5bNUF1F-3xUfl3Pa8ihPfDom8bB08JFC88N6q3uodgfoDF5k_IsTG83tadEmXxQa-2a=s240-c-k-c0x00ffffff-no-rj","YouTube":{"subscriber":{"tag":"has","count":1260},"id":"UC30Dj1DKVYk4kC8iWAjKbRg"},"popularVideo":{"type":"YouTube","id":"DI56okfTMWk"},"nationality":"TW","livestreams":[{"title":"【衝時數耐久直播】跟主播一起在台北車站睡覺好不好?【終迴謬 Shuukai Myu】","videoUrl":"https://www.youtube.com/watch?v=chAGLVq3OUg","thumbnailUrl":"https://i.ytimg.com/vi/chAGLVq3OUg/mqdefault_live.jpg","startTime":"2025-02-23T14:02:23.0000000\u002B00:00"}]}}