{"VTuber":{"id":"e0cd8e719dc64b5f9c171736bbaff6f7","activity":"active","name":"皮崎君","imgUrl":"https://yt3.ggpht.com/NA4rvXfod8fFs_7dkW7wgwOkTFxNLsA6t3l5-vuy-t_GiXu8IKQsd2KFLAXhoGqEOED3q2BE_w=s240-c-k-c0x00ffffff-no-rj","YouTube":{"subscriber":{"tag":"has","count":5940},"id":"UCDfSlmf3E16f1k_oz7LecFw"},"popularVideo":{"type":"YouTube","id":"g_w1FJqYXT4"},"nationality":"TW","debutDate":"2024-09-20","livestreams":[{"title":"﹝救世者之樹-新世界﹞聽說今天有新魔神可以玩，這遊戲是不是就是想讓我忙死阿 #VTuber#救世者之樹新世界創作激勵計劃 #救世者之樹新世界","videoUrl":"https://www.youtube.com/watch?v=Gg1zeYTxyEg","thumbnailUrl":"https://i.ytimg.com/vi/Gg1zeYTxyEg/mqdefault_live.jpg","startTime":"2025-01-23T07:39:57.0000000\u002B00:00"}]}}