{"VTuber":{"id":"f0a395b14fa34e64ba1aaedb906c7dd3","activity":"active","name":"諾菈","imgUrl":"https://yt3.ggpht.com/H4QD20ezHSBNRjgnmo58UykimmZVAZxqI-8_4liMvLXKnxHOTlqV_Fz4_4xw39dCLZfXWOpoOQ=s240-c-k-c0x00ffffff-no-rj","YouTube":{"subscriber":{"tag":"has","count":19400},"id":"UCmkENWGZeOKjJdeXhY0yPkg"},"popularVideo":{"type":"YouTube","id":"U1W4O3IpkY8"},"group":"比爾數位科技","nationality":"TW","debutDate":"2024-10-09","livestreams":[{"title":"【傳說對決】今日排位最後一天，希望和大家一起摘星星，謝謝本季大家的幫忙 | ✧ 諾菈 Nolla 傳說對決直播","videoUrl":"https://www.youtube.com/watch?v=_D1mAJlM6IY","thumbnailUrl":"https://i.ytimg.com/vi/_D1mAJlM6IY/mqdefault_live.jpg","startTime":"2025-01-07T12:30:00.0000000\u002B00:00"},{"title":"\uD83D\uDD34【崩壞：星穹鐵道】2.2主線(下)列車組能否封印星核？星期日的七休日會實現嗎？  | ✧ 諾菈Nolla | 崩鐵直播","videoUrl":"https://www.youtube.com/watch?v=o-sGhlVXICE","thumbnailUrl":"https://i.ytimg.com/vi/o-sGhlVXICE/mqdefault_live.jpg","startTime":"2025-01-08T12:30:00.0000000\u002B00:00"},{"title":"【幻獸帕魯 】要不要一起來抓帕魯？和箱內姐姐們的遊戲日｜會員場次 Fit. @VtuberSenfina @VtuberBill ｜◇ 諾菈Nolla","videoUrl":"https://www.youtube.com/watch?v=v_3xi5SoPs8","thumbnailUrl":"https://i.ytimg.com/vi/v_3xi5SoPs8/mqdefault_live.jpg","startTime":"2025-01-11T12:00:00.0000000\u002B00:00"}]}}