{"VTuber":{"id":"f7c8264349654390a5e39810dc012a38","activity":"active","name":"星見遙","imgUrl":"https://yt3.ggpht.com/JkR39_wONb5jPwMCLeDY-tjKeT97CPYKjJIQPHW5R6poogfM41BW2VsfmRTIrvfYE4SpA2YMgQ=s240-c-k-c0x00ffffff-no-rj","YouTube":{"subscriber":{"tag":"has","count":20000},"id":"UCl1RVJbkPnpNbO9-CsDqPmQ"},"popularVideo":{"type":"YouTube","id":"313APy-Iccs"},"nationality":"TW","debutDate":"2020-11-13","livestreams":[{"title":"◖同步視聽◗ 一輩子？《BanG Dream! It\u0027s MyGO!!!!!》第1集 ~ 第6集 ※初見【星見遙】","videoUrl":"https://www.youtube.com/watch?v=lxU_C2iQpLA","thumbnailUrl":"https://i.ytimg.com/vi/lxU_C2iQpLA/mqdefault_live.jpg","startTime":"2025-01-07T12:30:00.0000000\u002B00:00"}]}}