{"VTuber":{"id":"f7c8264349654390a5e39810dc012a38","activity":"active","name":"星見遙","imgUrl":"https://yt3.ggpht.com/gBYxfPuWQrB1-Jc5TB2j4veyhX6XGkH3th4Yy_9Vjtbevd-en77uffYg9KytIgRoziredn2LqA=s240-c-k-c0x00ffffff-no-rj","YouTube":{"subscriber":{"tag":"has","count":20000},"id":"UCl1RVJbkPnpNbO9-CsDqPmQ"},"popularVideo":{"type":"YouTube","id":"-QoXnY_49xI"},"nationality":"TW","debutDate":"2020-11-13","livestreams":[{"title":"◖咕咕披薩◗ 辛酸打工流出，被朋友送了這款來玩...我有不妙的預感【星見遙】","videoUrl":"https://www.youtube.com/watch?v=hDOg_1lfxvI","thumbnailUrl":"https://i.ytimg.com/vi/hDOg_1lfxvI/mqdefault_live.jpg","startTime":"2025-02-21T13:00:00.0000000\u002B00:00"}]}}