{"VTuber":{"id":"f99429e8c2324c5db10f11c3a2c51b5d","activity":"active","name":"Print-2301","imgUrl":"https://yt3.ggpht.com/OfbGb1avicZAVBkeOYpMOFr6UTgIJB-Dgp27e2BT787LpSgW6WcUGnAWBTLMoHE6Qkdx9L3pcA=s240-c-k-c0x00ffffff-no-rj","YouTube":{"subscriber":{"tag":"has","count":1910},"id":"UCxdrWaJciHe2O3uZm24iaOQ"},"popularVideo":{"type":"YouTube","id":"wanrzHtSqCw"},"nationality":"TW","debutDate":"2024-08-30","livestreams":[{"title":"【突發!】❰週表製作❱  睡醒了嗎?哪裡有小豬!\uD83E\uDD16","videoUrl":"https://www.youtube.com/watch?v=efKTw6svf_k","thumbnailUrl":"https://i.ytimg.com/vi/efKTw6svf_k/mqdefault_live.jpg","startTime":"2025-02-10T01:00:00.0000000\u002B00:00"},{"title":"【GameMode】2301【突發!】❰咕咕披薩：送披薩到太空站？老闆，這不對啊！❱ pt.2   關於我想送披薩到UFO而不是玩UFO這件事 \uD83E\uDD16","videoUrl":"https://www.youtube.com/watch?v=BBySjyvF55E","thumbnailUrl":"https://i.ytimg.com/vi/BBySjyvF55E/mqdefault_live.jpg","startTime":"2025-02-10T05:00:00.0000000\u002B00:00"}]}}